clientAPI/__init__.py
clientAPI/base.py
clientAPI/client.py
clientAPI/mixin.py
clientAPI/setup.py
clientAPI/utils.py
clientAPI/objects/__init__.py
clientAPI/objects/accelerator_configuration.py
clientAPI/objects/application.py
clientAPI/objects/architecture.py
clientAPI/objects/benchmarks.py
clientAPI/objects/codename.py
clientAPI/objects/continent.py
clientAPI/objects/country.py
clientAPI/objects/file_system.py
clientAPI/objects/firmware.py
clientAPI/objects/floating_point_unit.py
clientAPI/objects/genera.py
clientAPI/objects/green500.py
clientAPI/objects/has_accelerator.py
clientAPI/objects/has_interconnect.py
clientAPI/objects/has_memory.py
clientAPI/objects/has_operating_system.py
clientAPI/objects/has_processor.py
clientAPI/objects/interconnect.py
clientAPI/objects/interconnect_configuration.py
clientAPI/objects/interconnect_family.py
clientAPI/objects/isas.py
clientAPI/objects/manufacturer.py
clientAPI/objects/memory_configuration.py
clientAPI/objects/microarchitectures.py
clientAPI/objects/ontology_type.py
clientAPI/objects/operating_system.py
clientAPI/objects/operating_system_configuration.py
clientAPI/objects/other_software.py
clientAPI/objects/pointer.py
clientAPI/objects/processor_configuration.py
clientAPI/objects/processor_hierarchy.py
clientAPI/objects/processors.py
clientAPI/objects/region.py
clientAPI/objects/segment.py
clientAPI/objects/spec1995.py
clientAPI/objects/spec2000.py
clientAPI/objects/spec2006.py
clientAPI/objects/spec2017.py
clientAPI/objects/system_configuration.py
clientAPI/objects/system_family.py
clientAPI/objects/system_manufacturer.py
clientAPI/objects/system_state.py
clientAPI/objects/systems.py
clientAPI/objects/top500.py
clientAPI/objects/top500_ranks.py
clientAPI/objects/used_to_run.py
csgapi/__init__.py
csgapi/base.py
csgapi/client.py
csgapi/mixin.py
csgapi/setup.py
csgapi/utils.py
csgapi/objects/__init__.py
csgapi/objects/accelerator_configuration.py
csgapi/objects/application.py
csgapi/objects/architecture.py
testcsg-0.1.10.dist-info/METADATA
testcsg-0.1.10.dist-info/WHEEL
testcsg-0.1.10.dist-info/top_level.txt
testcsg-0.1.10.dist-info/RECORD
